slidescore/__init__.py
slidescore/bin_data.py
slidescore/export_data.py
slidescore/slidescore.py
slidescore/lib/AnnoClasses.py
slidescore/lib/Decoder.py
slidescore/lib/Encoder.py
slidescore/lib/PolygonContainer.py
slidescore/lib/__init__.py
slidescore/lib/image_utils.py
slidescore/lib/omega_encoder.py
slidescore/lib/polygon_encoder.py
slidescore/lib/simplify.py
slidescore/lib/utils.py
slidescore_sdk-1.5.0.dist-info/LICENSE
slidescore_sdk-1.5.0.dist-info/METADATA
slidescore_sdk-1.5.0.dist-info/WHEEL
slidescore_sdk-1.5.0.dist-info/top_level.txt
slidescore_sdk-1.5.0.dist-info/RECORD
