Metadata-Version: 2.1
Name: slidescore-sdk
Version: 1.5.0
Summary: SDK for using the API of Slide Score
Home-page: https://github.com/SlideScore/SlideScore-python-sdk
Author: Slide Score B.V.
Author-email: info@slidescore.com
Keywords: slidescore,slide score,sdk,api
Classifier: Programming Language :: Python :: 3
Classifier: License :: OSI Approved :: MIT License
Classifier: Operating System :: OS Independent
Classifier: Intended Audience :: Developers
Classifier: Topic :: Software Development :: Libraries :: Python Modules
License-File: LICENSE
Requires-Dist: marshmallow<3,>=2
Requires-Dist: requests
Requires-Dist: tuspy
Requires-Dist: bitarray<3,>=2.7
Requires-Dist: Brotli>=1.0.0
Requires-Dist: msgpack>=1.0.0
Requires-Dist: pypng==0.20220715.0
